.
MANIFEST.in
README.md
setup.py
tweeds/__init__.py
tweeds/main.py
tweeds/query.py
tweeds/tweet_scrape.py
tweeds.egg-info/PKG-INFO
tweeds.egg-info/SOURCES.txt
tweeds.egg-info/dependency_links.txt
tweeds.egg-info/entry_points.txt
tweeds.egg-info/requires.txt
tweeds.egg-info/top_level.txt