Metadata-Version: 1.0
Name: tweeds
Version: 2.1.1
Summary: An advanced Twitter scraping & OSINT tool.
Home-page: https://github.com/achyuthjoism/Twitter-OSINT
Author: Achyuth Jois M
Author-email: developer.arjm@gmail.com
License: MIT
Platform: UNKNOWN
